{
  "presets": {
    "front_standing_grabbingbreasts": {
      "name": "front standing grabbingBreasts",
      "categories": {
        "Angulo": "(((high angle)),((from top))), ((Wide angle lens)),",
        "Ojos": "blue eyes,half-closed eyes,",
        "Expresion facial boca": "inminent blowjob, smile, open mouth,",
        "Postura cabeza": "",
        "Direccion mirada personaje": "looking at viewer,",
        "Pose actitud global": "standing,",
        "Pose brazos": "arms away from body, loose arms, relaxed arms, dainty hands, limp wrists,",
        "Pose piernas": "",
        "Orientacion personaje": "((facing forward)),",
        "Actitud emocion": "",
        "Nsfw": "pov man hand, grabbing another's breast,",
        "Objetos interaccion": "",
        "Objetos escenario": "",
        "Mirada espectador": "((close-up)),"
      },
      "images": [
        "image_1.png",
        "image_2.png",
        "image_3.png"
      ],
      "created_at": "2025-12-30T16:54:05.389229"
    }
  }
}